{
    "id": 8060,
    "name": "MEGACOLLAB",
    "author": "TurboFlash",
    "creators": [],
    "verifier": "TurboFlash",
    "verification": "https://youtu.be/mHNoigmkVAg",
    "percentToQualify": 100,
    "password": "Free Copy",
    "records": [
        {
            "user": "SomeoneUnknown",
            "link": "https://youtu.be/eo0msPNP4EE",
            "percent": 100,
            "hz": 60
        }, 
        {
            "user": "abner2008",
            "link": "https://youtu.be/Vrluku2nB-A?si=u6KeLXzTqOeiPVhp ",
            "percent": 100,
            "hz": 90,
            "mobile": true
        },
        {
            "user": "Beli9002",
            "link": "https://youtu.be/M9uR91gphmE?si=0xiTIQYmAmcaM6jL&t=1m2s",
            "percent": 100,
            "hz": 144
        }
    ]
}
